webarena/test.raw.json
webarena/agent/__init__.py
webarena/agent/agent.py
webarena/browser_env/__init__.py
webarena/browser_env/actions.py
webarena/browser_env/async_envs.py
webarena/browser_env/auto_login.py
webarena/browser_env/constants.py
webarena/browser_env/env_config.py
webarena/browser_env/envs.py
webarena/browser_env/helper_functions.py
webarena/browser_env/processors.py
webarena/browser_env/py.typed
webarena/browser_env/trajectory.py
webarena/browser_env/utils.py
webarena/evaluation_harness/__init__.py
webarena/evaluation_harness/evaluators.py
webarena/evaluation_harness/helper_functions.py
webarena/llms/__init__.py
webarena/llms/lm_config.py
webarena/llms/tokenizers.py
webarena/llms/utils.py
webarena/llms/providers/hf_utils.py
webarena/llms/providers/openai_utils.py
libwebarena-0.0.4.dist-info/LICENSE
libwebarena-0.0.4.dist-info/METADATA
libwebarena-0.0.4.dist-info/WHEEL
libwebarena-0.0.4.dist-info/top_level.txt
libwebarena-0.0.4.dist-info/RECORD
